Metadata-Version: 2.1
Name: ayek-probability
Version: 1.0
Summary: gaussian probability
Author: Augustine Ayekor
Author-email: augustineayekor@gmail.com
